glitor/__init__.py
glitor/asgi.py
glitor/config.py
glitor/main.py
glitor/notifier.py
glitor-0.1.0.dist-info/WHEEL
glitor-0.1.0.dist-info/METADATA
glitor-0.1.0.dist-info/RECORD
